cacha/__init__.py
cacha/cacha_io.py
cacha/hashing_tools.py
cacha/logging_utils.py
cacha/manager.py
cacha/store/.DS_Store
cacha/store/__init__.py
cacha/store/pickledb_store.py
cacha/store/store_interface.py
cacha/tests/__init__.py
cacha/tests/pip_install_test.sh
cacha/tests/test_data_structures.py
cacha/tests/test_standard_usage.py
cacha/tests/test_store.py
cacha/tests/utils.py
cacha/version.py
cacha-1.0.0.dist-info/LICENSE
cacha-1.0.0.dist-info/WHEEL
cacha-1.0.0.dist-info/METADATA
cacha-1.0.0.dist-info/RECORD
