Metadata-Version: 2.1
Name: cacha
Version: 1.0.0
Summary: A simple cache context manager for Data Scientists.
Home-page: https://python-poetry.org/
License: Apache-2.0
Keywords: python,cache,data science
Author: Dawid Smoleń
Author-email: smolendawid@gmail.com
Maintainer: Dawid Smoleń
Maintainer-email: smolendawid@gmail.com
Requires-Python: >=3.8,<4.0
Classifier: License :: OSI Approved :: Apache Software License
Classifier: Programming Language :: Python :: 3
Classifier: Programming Language :: Python :: 3.10
Classifier: Programming Language :: Python :: 3.8
Classifier: Programming Language :: Python :: 3.9
Requires-Dist: numpy (>=1.23.2,<2.0.0)
Requires-Dist: pandas (>=1.4.3,<2.0.0)
Requires-Dist: pickleDB (>=0.9.2,<0.10.0)
Project-URL: Repository, https://github.com/smolendawid/cache-manager
